blue_brain_token_fetch/.coverage
blue_brain_token_fetch/__init__.py
blue_brain_token_fetch/__init__.pyc
blue_brain_token_fetch/duration_converter.py
blue_brain_token_fetch/job.py
blue_brain_token_fetch/nexus_token_fetch.py
blue_brain_token_fetch/token_fetcher_base.py
blue_brain_token_fetch/token_fetcher_service.py
blue_brain_token_fetch/token_fetcher_user.py
tests/__init__.py
tests/conftest.py
tests/test_duration_converter.py
tests/test_token_fetcher_base.py
tests/test_token_fetcher_cli.py
tests/test_token_fetcher_service.py
tests/test_token_fetcher_user.py
tests/tests_data/empty_keycloak_config.yaml
tests/tests_data/regular_keycloak_config.yaml
tests/tests_data/regular_keycloak_config_invalid_client_id.yaml
tests/tests_data/regular_keycloak_config_invalid_realm.yaml
tests/tests_data/regular_keycloak_config_invalid_server_url.yaml
tests/tests_data/regular_keycloak_config_with_password.yaml
tests/tests_data/service_keycloak_config.yaml
blue_brain_token_fetch-3.0.2.dist-info/AUTHORS.txt
blue_brain_token_fetch-3.0.2.dist-info/LICENSE.txt
blue_brain_token_fetch-3.0.2.dist-info/METADATA
blue_brain_token_fetch-3.0.2.dist-info/WHEEL
blue_brain_token_fetch-3.0.2.dist-info/entry_points.txt
blue_brain_token_fetch-3.0.2.dist-info/top_level.txt
blue_brain_token_fetch-3.0.2.dist-info/RECORD
